html_chunking/__init__.py
html_chunking-0.0.4.dist-info/LICENSE
html_chunking-0.0.4.dist-info/METADATA
html_chunking-0.0.4.dist-info/WHEEL
html_chunking-0.0.4.dist-info/top_level.txt
html_chunking-0.0.4.dist-info/RECORD
