Metadata-Version: 2.1
Name: html_chunking
Version: 0.0.4
Summary: A Python package for token-aware HTML chunking that preserves structure and attributes, with optional cleaning and attribute length control.
Author-email: Jiarun Liu <liujiarun01@126.com>
Maintainer-email: Jiarun Liu <liujiarun01@126.com>
Project-URL: Homepage, https://github.com/KLGR123/html_chunking
Project-URL: Issues, https://github.com/KLGR123/html_chunking
Classifier: Programming Language :: Python :: 3
Classifier: License :: OSI Approved :: MIT License
Classifier: Operating System :: OS Independent
Requires-Python: >=3.8
License-File: LICENSE
Requires-Dist: beautifulsoup4 >4.12.0
Requires-Dist: cssutils >2.11.0
Requires-Dist: tiktoken >0.5.0
